goveelights/__init__.py
goveelights/client.py
goveelights/color.py
goveelights/consts.py
goveelights/device.py
goveelights/exceptions.py
goveelights/hub.py
goveelights/settings.py
goveelights-0.1.2.dist-info/LICENSE
goveelights-0.1.2.dist-info/METADATA
goveelights-0.1.2.dist-info/WHEEL
goveelights-0.1.2.dist-info/top_level.txt
goveelights-0.1.2.dist-info/RECORD
