Metadata-Version: 2.1
Name: goveelights
Version: 0.1.2
Summary: A small package to interact with the Govee API.
Home-page: https://github.com/arcanearronax/govee_lights
Author: arcanearronax
License: UNKNOWN
Project-URL: Bug Tracker, https://github.com/arcanearronax/govee_lights/issues
Keywords: govee,device,lights,client
Platform: UNKNOWN
Classifier: Programming Language :: Python :: 3.8
Classifier: License :: OSI Approved :: MIT License
Classifier: Operating System :: OS Independent
Requires-Python: >=3.8
License-File: LICENSE
